celery_haystack/__init__.py
celery_haystack/conf.py
celery_haystack/indexes.py
celery_haystack/models.py
celery_haystack/signals.py
celery_haystack/tasks.py
celery_haystack/test_settings.py
celery_haystack/utils.py
celery_haystack/tests/__init__.py
celery_haystack/tests/models.py
celery_haystack/tests/search_indexes.py
celery_haystack/tests/search_sites.py
celery_haystack/tests/tests.py
celery_haystack-0.10.dist-info/DESCRIPTION.rst
celery_haystack-0.10.dist-info/METADATA
celery_haystack-0.10.dist-info/metadata.json
celery_haystack-0.10.dist-info/RECORD
celery_haystack-0.10.dist-info/top_level.txt
celery_haystack-0.10.dist-info/WHEEL
