Metadata-Version: 2.0
Name: celery-haystack
Version: 0.10
Summary: An app for integrating Celery with Haystack.
Home-page: http://celery-haystack.rtfd.org/
Author: Jannis Leidel
Author-email: jannis@leidel.info
License: UNKNOWN
Platform: UNKNOWN
Classifier: Development Status :: 4 - Beta
Classifier: Environment :: Web Environment
Classifier: Framework :: Django
Classifier: Intended Audience :: Developers
Classifier: License :: OSI Approved :: BSD License
Classifier: Operating System :: OS Independent
Classifier: Programming Language :: Python
Classifier: Programming Language :: Python :: 2.6
Classifier: Programming Language :: Python :: 2.7
Classifier: Programming Language :: Python :: 3.3
Classifier: Programming Language :: Python :: 3.4
Classifier: Topic :: Utilities
Requires-Dist: django-appconf>=0.4.1
